farms/__init__.py
farms/disc.py
farms/earth_periodic_terms.csv
farms/farms.py
farms/farms_dni.py
farms/sun_earth_radius_vector.csv
farms/utilities.py
farms/version.py
NREL_farms-1.0.6.dist-info/LICENSE
NREL_farms-1.0.6.dist-info/METADATA
NREL_farms-1.0.6.dist-info/WHEEL
NREL_farms-1.0.6.dist-info/top_level.txt
NREL_farms-1.0.6.dist-info/RECORD
