Metadata-Version: 2.1
Name: NREL-farms
Version: 1.0.6
Summary: The Fast All-sky Radiation Model for Solar applications (FARMS)
Home-page: https://github.com/NREL/farms
Author: Grant Buster
Author-email: grant.buster@nrel.gov
License: BSD 3-Clause
Keywords: farms
Platform: UNKNOWN
Classifier: Development Status :: 4 - Beta
Classifier: Intended Audience :: Science/Research
Classifier: License :: OSI Approved :: BSD License
Classifier: Natural Language :: English
Classifier: Programming Language :: Python :: 3.7
Classifier: Programming Language :: Python :: 3.8
Classifier: Programming Language :: Python :: 3.9
Requires-Python: >=3.7
Requires-Dist: numpy >=1.17
Requires-Dist: pandas >=0.25
Provides-Extra: dev
Requires-Dist: pytest >=5.2 ; extra == 'dev'
Requires-Dist: flake8 ; extra == 'dev'
Requires-Dist: pre-commit ; extra == 'dev'
Requires-Dist: pylint ; extra == 'dev'
Provides-Extra: test
Requires-Dist: pytest >=5.2 ; extra == 'test'
